{
 "generatedAt": "2026-07-12T12:10:54.110Z",
 "generatedAtVN": "19:10 12-07",
 "order": [
  "BTC",
  "ETH",
  "SOL",
  "BNB",
  "XAU"
 ],
 "coins": {
  "BTC": {
   "symbol": "BTC",
   "tvSymbol": "BINANCE:BTCUSDT",
   "liveBase": "BTC",
   "price": {
    "last": 63980.8,
    "change24h": 0.2496024067124715,
    "high24h": 64500,
    "low24h": 63652.9
   },
   "council": {
    "direction": "LONG",
    "confidence": "low",
    "consensus": 0.188,
    "agreement": 55,
    "counterTrend": false,
    "tiers": {
     "regime": {
      "dir": "LONG",
      "score": 0.257
     },
     "setup": {
      "dir": "LONG",
      "gated": false
     },
     "trigger": {
      "dir": "NEUTRAL",
      "gated": false
     }
    },
    "members": [
     {
      "name": "Ichimoku",
      "vote": 1,
      "weight": 1.94,
      "tier": "regime",
      "dot": "green"
     },
     {
      "name": "ETFFlow",
      "vote": 0.8,
      "weight": 1.2,
      "tier": "regime",
      "dot": "green"
     },
     {
      "name": "Volume",
      "vote": 1,
      "weight": 0.91,
      "tier": "trigger",
      "dot": "green"
     },
     {
      "name": "Momentum",
      "vote": -0.65,
      "weight": 1.39,
      "tier": "trigger",
      "dot": "red"
     },
     {
      "name": "Trend",
      "vote": -0.4,
      "weight": 2.47,
      "tier": "regime",
      "dot": "red"
     },
     {
      "name": "Cycle",
      "vote": -0.5,
      "weight": 1.2,
      "tier": "regime",
      "dot": "red"
     },
     {
      "name": "Patterns",
      "vote": 0.6,
      "weight": 1.85,
      "tier": "setup",
      "dot": "green"
     },
     {
      "name": "Sentiment",
      "vote": 0.3,
      "weight": 1,
      "tier": "regime",
      "dot": "green"
     },
     {
      "name": "Macro",
      "vote": -0.44,
      "weight": 0.5,
      "tier": "regime",
      "dot": "red"
     },
     {
      "name": "SMC",
      "vote": 0.09,
      "weight": 1.53,
      "tier": "setup",
      "dot": "green"
     },
     {
      "name": "MeanReversion",
      "vote": 0,
      "weight": 0.63,
      "tier": "setup",
      "dot": "gray"
     },
     {
      "name": "Derivatives",
      "vote": 0,
      "weight": 0.7,
      "tier": "trigger",
      "dot": "gray"
     }
    ]
   },
   "expert": {
    "verdict": "3 khung đồng pha LONG — thuận xu hướng, vào theo style.",
    "scalp": null,
    "day": null,
    "swing": {
     "dir": "LONG",
     "entry": [
      62748,
      63117
     ],
     "sl": 62118,
     "tp": [
      63485,
      64679,
      66610
     ],
     "rr": 2.1,
     "method": "fibonacci",
     "fib": {
      "f0": 61555,
      "f382": 63485,
      "f500": 63117,
      "f618": 62748,
      "f786": 62223,
      "f100": 64679,
      "ext1618": 66610
     },
     "meetsMinRR": true
    }
   },
   "indicators": [
    {
     "tf": "1D",
     "rsi": 52.87,
     "macd": "bull",
     "stoch": 89.81,
     "st": "down",
     "extra": "ADX 24 · EMA death"
    },
    {
     "tf": "4H",
     "rsi": 54.72,
     "macd": "bear",
     "stoch": 31.96,
     "st": "up",
     "extra": "Ichi above"
    },
    {
     "tf": "1H",
     "rsi": 48,
     "macd": "bear",
     "stoch": 56,
     "st": -1,
     "extra": "VWAP below"
    },
    {
     "tf": "15m",
     "rsi": 53,
     "macd": "bull",
     "stoch": 74,
     "st": 1,
     "extra": ""
    }
   ],
   "cycle": {
    "regime": "Pullback/bear-rally (giữa MA200W và MA50W)",
    "ma200w": 63222.75,
    "mayer": 0.87,
    "weeklyMacdBear": true,
    "supports": [
     {
      "ma": "MA200W",
      "level": 63223,
      "distPct": -1.2
     },
     {
      "ma": "MA300W",
      "level": 55060,
      "distPct": -13.9
     }
    ],
    "piGapPct": 5.5
   },
   "derivatives": {
    "fundingRate": 0.00003,
    "coinbasePremium": {
     "gap": -18.51,
     "signal": "⚪ trung tính"
    }
   },
   "levels": [
    {
     "price": 63117,
     "label": "Entry LONG",
     "color": "#22c55e"
    },
    {
     "price": 62118,
     "label": "SL",
     "color": "#f59e0b"
    },
    {
     "price": 63485,
     "label": "TP1",
     "color": "#3b82f6"
    },
    {
     "price": 63222.75,
     "label": "MA200W",
     "color": "#a855f7"
    },
    {
     "price": 61555,
     "label": "Hỗ trợ",
     "color": "#64748b"
    }
   ]
  },
  "ETH": {
   "symbol": "ETH",
   "tvSymbol": "BINANCE:ETHUSDT",
   "liveBase": "ETH",
   "price": {
    "last": 1803.48,
    "change24h": 0.8398286794225199,
    "high24h": 1830.6,
    "low24h": 1781.28
   },
   "council": {
    "direction": "LONG",
    "confidence": "medium",
    "consensus": 0.279,
    "agreement": 63,
    "counterTrend": false,
    "tiers": {
     "regime": {
      "dir": "LONG",
      "score": 0.287
     },
     "setup": {
      "dir": "LONG",
      "gated": false
     },
     "trigger": {
      "dir": "LONG",
      "gated": false
     }
    },
    "members": [
     {
      "name": "Ichimoku",
      "vote": 1,
      "weight": 1.94,
      "tier": "regime",
      "dot": "green"
     },
     {
      "name": "Patterns",
      "vote": 1,
      "weight": 1.85,
      "tier": "setup",
      "dot": "green"
     },
     {
      "name": "SMC",
      "vote": -0.72,
      "weight": 1.53,
      "tier": "setup",
      "dot": "red"
     },
     {
      "name": "ETFFlow",
      "vote": 0.8,
      "weight": 1.2,
      "tier": "regime",
      "dot": "green"
     },
     {
      "name": "Volume",
      "vote": 1,
      "weight": 0.91,
      "tier": "trigger",
      "dot": "green"
     },
     {
      "name": "Trend",
      "vote": -0.4,
      "weight": 2.47,
      "tier": "regime",
      "dot": "red"
     },
     {
      "name": "Cycle",
      "vote": -0.3,
      "weight": 1.2,
      "tier": "regime",
      "dot": "red"
     },
     {
      "name": "MeanReversion",
      "vote": 0.5,
      "weight": 0.63,
      "tier": "setup",
      "dot": "green"
     },
     {
      "name": "Sentiment",
      "vote": 0.3,
      "weight": 1,
      "tier": "regime",
      "dot": "green"
     },
     {
      "name": "Macro",
      "vote": -0.53,
      "weight": 0.5,
      "tier": "regime",
      "dot": "red"
     },
     {
      "name": "Momentum",
      "vote": 0.14,
      "weight": 1.39,
      "tier": "trigger",
      "dot": "green"
     },
     {
      "name": "Derivatives",
      "vote": 0.15,
      "weight": 0.7,
      "tier": "trigger",
      "dot": "green"
     }
    ]
   },
   "expert": {
    "verdict": "3 khung đồng pha LONG — thuận xu hướng, vào theo style.",
    "scalp": null,
    "day": null,
    "swing": {
     "dir": "LONG",
     "entry": [
      1759,
      1772
     ],
     "sl": 1735,
     "tp": [
      1786,
      1831,
      1903
     ],
     "rr": 2.1,
     "method": "fibonacci",
     "fib": {
      "f0": 1714,
      "f382": 1786,
      "f500": 1772,
      "f618": 1759,
      "f786": 1739,
      "f100": 1831,
      "ext1618": 1903
     },
     "meetsMinRR": true
    }
   },
   "indicators": [
    {
     "tf": "1D",
     "rsi": 58.08,
     "macd": "bull",
     "stoch": 89.51,
     "st": "up",
     "extra": "ADX 24 · EMA death"
    },
    {
     "tf": "4H",
     "rsi": 56.34,
     "macd": "bull",
     "stoch": 52.7,
     "st": "up",
     "extra": "Ichi above"
    },
    {
     "tf": "1H",
     "rsi": 50,
     "macd": "bear",
     "stoch": 65,
     "st": -1,
     "extra": "VWAP below"
    },
    {
     "tf": "15m",
     "rsi": 53,
     "macd": "bull",
     "stoch": 62,
     "st": 1,
     "extra": ""
    }
   ],
   "cycle": {
    "regime": "DEEP BEAR / vùng đáy chu kỳ",
    "ma200w": 2478.32,
    "mayer": 0.81,
    "weeklyMacdBear": false,
    "supports": [],
    "piGapPct": 1.4
   },
   "derivatives": {
    "fundingRate": -0.000006,
    "coinbasePremium": {
     "gap": 0.17,
     "signal": "⚪ trung tính"
    }
   },
   "levels": [
    {
     "price": 1772,
     "label": "Entry LONG",
     "color": "#22c55e"
    },
    {
     "price": 1735,
     "label": "SL",
     "color": "#f59e0b"
    },
    {
     "price": 1786,
     "label": "TP1",
     "color": "#3b82f6"
    },
    {
     "price": 2478.32,
     "label": "MA200W",
     "color": "#a855f7"
    },
    {
     "price": 1714,
     "label": "Hỗ trợ",
     "color": "#64748b"
    }
   ]
  },
  "SOL": {
   "symbol": "SOL",
   "tvSymbol": "BINANCE:SOLUSDT",
   "liveBase": "SOL",
   "price": {
    "last": 76.81,
    "change24h": 0.0912170966901224,
    "high24h": 78.82,
    "low24h": 75.67
   },
   "council": {
    "direction": "SHORT",
    "confidence": "medium",
    "consensus": -0.364,
    "agreement": 63,
    "counterTrend": false,
    "tiers": {
     "regime": {
      "dir": "SHORT",
      "score": -0.727
     },
     "setup": {
      "dir": "SHORT",
      "gated": false
     },
     "trigger": {
      "dir": "NEUTRAL",
      "gated": true
     }
    },
    "members": [
     {
      "name": "Ichimoku",
      "vote": -1,
      "weight": 1.94,
      "tier": "regime",
      "dot": "red"
     },
     {
      "name": "Patterns",
      "vote": -0.76,
      "weight": 1.85,
      "tier": "setup",
      "dot": "red"
     },
     {
      "name": "Trend",
      "vote": -1,
      "weight": 2.47,
      "tier": "regime",
      "dot": "red"
     },
     {
      "name": "SMC",
      "vote": 0.21,
      "weight": 1.53,
      "tier": "setup",
      "dot": "green"
     },
     {
      "name": "Volume",
      "vote": 0.4,
      "weight": 0.91,
      "tier": "trigger",
      "dot": "green"
     },
     {
      "name": "MeanReversion",
      "vote": 0.5,
      "weight": 0.63,
      "tier": "setup",
      "dot": "green"
     },
     {
      "name": "Sentiment",
      "vote": 0.3,
      "weight": 1,
      "tier": "regime",
      "dot": "green"
     },
     {
      "name": "Macro",
      "vote": -0.53,
      "weight": 0.5,
      "tier": "regime",
      "dot": "red"
     },
     {
      "name": "Momentum",
      "vote": -0.1,
      "weight": 1.39,
      "tier": "trigger",
      "dot": "red"
     },
     {
      "name": "Derivatives",
      "vote": 0.15,
      "weight": 0.7,
      "tier": "trigger",
      "dot": "green"
     },
     {
      "name": "Cycle",
      "vote": 0,
      "weight": 1.2,
      "tier": "regime",
      "dot": "gray"
     },
     {
      "name": "ETFFlow",
      "vote": 0,
      "weight": 1.2,
      "tier": "regime",
      "dot": "gray"
     }
    ]
   },
   "expert": {
    "verdict": "3 khung đồng pha SHORT — thuận xu hướng, vào theo style.",
    "scalp": null,
    "day": {
     "dir": "SHORT",
     "entry": [
      77.25,
      77.62
     ],
     "sl": 78.24,
     "tp": [
      76.87,
      75.67,
      73.72
     ],
     "rr": 2.18,
     "method": "fib",
     "fib": {
      "f0": 78.82,
      "f382": 76.87,
      "f500": 77.25,
      "f618": 77.62,
      "f786": 78.15,
      "f100": 75.67,
      "ext1618": 73.72
     },
     "meetsMinRR": true,
     "reasons": [
      "VWAP↓",
      "RSI43"
     ]
    },
    "swing": {
     "dir": "SHORT",
     "entry": [
      79,
      80
     ],
     "sl": 81,
     "tp": [
      78,
      76,
      71
     ],
     "rr": 2.2,
     "method": "fibonacci",
     "fib": {
      "f0": 82.78,
      "f382": 78.39,
      "f500": 79.22,
      "f618": 80.06,
      "f786": 81.26,
      "f100": 75.67,
      "ext1618": 71.28
     },
     "meetsMinRR": true
    }
   },
   "indicators": [
    {
     "tf": "1D",
     "rsi": 51.21,
     "macd": "bear",
     "stoch": 46.72,
     "st": "up",
     "extra": "ADX 19 · EMA death"
    },
    {
     "tf": "4H",
     "rsi": 39.91,
     "macd": "bear",
     "stoch": 28.86,
     "st": "down",
     "extra": "Ichi below"
    },
    {
     "tf": "1H",
     "rsi": 43,
     "macd": "bull",
     "stoch": 51,
     "st": -1,
     "extra": "VWAP below"
    },
    {
     "tf": "15m",
     "rsi": 52,
     "macd": "bull",
     "stoch": 49,
     "st": 1,
     "extra": ""
    }
   ],
   "cycle": {
    "regime": "DEEP BEAR / vùng đáy chu kỳ",
    "ma200w": null,
    "mayer": 0.84,
    "weeklyMacdBear": false,
    "supports": [],
    "piGapPct": -12.7
   },
   "derivatives": {
    "fundingRate": -0.000003,
    "coinbasePremium": {
     "gap": 0.02,
     "signal": "⚪ trung tính"
    }
   },
   "levels": [
    {
     "price": 80,
     "label": "Entry SHORT",
     "color": "#ef4444"
    },
    {
     "price": 81,
     "label": "SL",
     "color": "#f59e0b"
    },
    {
     "price": 78,
     "label": "TP1",
     "color": "#3b82f6"
    },
    {
     "price": 75.67,
     "label": "Hỗ trợ",
     "color": "#64748b"
    }
   ]
  },
  "BNB": {
   "symbol": "BNB",
   "tvSymbol": "BINANCE:BNBUSDT",
   "liveBase": "BNB",
   "price": {
    "last": 581.19,
    "change24h": 1.539187253223383,
    "high24h": 581.62,
    "low24h": 572.38
   },
   "council": {
    "direction": "LONG",
    "confidence": "medium",
    "consensus": 0.301,
    "agreement": 65,
    "counterTrend": false,
    "tiers": {
     "regime": {
      "dir": "LONG",
      "score": 0.4
     },
     "setup": {
      "dir": "LONG",
      "gated": false
     },
     "trigger": {
      "dir": "LONG",
      "gated": false
     }
    },
    "members": [
     {
      "name": "Ichimoku",
      "vote": 1,
      "weight": 1.94,
      "tier": "regime",
      "dot": "green"
     },
     {
      "name": "Patterns",
      "vote": 0.88,
      "weight": 1.85,
      "tier": "setup",
      "dot": "green"
     },
     {
      "name": "SMC",
      "vote": -0.42,
      "weight": 1.53,
      "tier": "setup",
      "dot": "red"
     },
     {
      "name": "Trend",
      "vote": -0.4,
      "weight": 2.47,
      "tier": "regime",
      "dot": "red"
     },
     {
      "name": "Momentum",
      "vote": 0.21,
      "weight": 1.39,
      "tier": "trigger",
      "dot": "green"
     },
     {
      "name": "Volume",
      "vote": 0.3,
      "weight": 0.91,
      "tier": "trigger",
      "dot": "green"
     },
     {
      "name": "Sentiment",
      "vote": 0.3,
      "weight": 1,
      "tier": "regime",
      "dot": "green"
     },
     {
      "name": "Macro",
      "vote": -0.53,
      "weight": 0.5,
      "tier": "regime",
      "dot": "red"
     },
     {
      "name": "MeanReversion",
      "vote": 0.2,
      "weight": 0.63,
      "tier": "setup",
      "dot": "green"
     },
     {
      "name": "Derivatives",
      "vote": 0.15,
      "weight": 0.7,
      "tier": "trigger",
      "dot": "green"
     },
     {
      "name": "Cycle",
      "vote": 0,
      "weight": 1.2,
      "tier": "regime",
      "dot": "gray"
     },
     {
      "name": "ETFFlow",
      "vote": 0,
      "weight": 1.2,
      "tier": "regime",
      "dot": "gray"
     }
    ]
   },
   "expert": {
    "verdict": "3 khung đồng pha LONG — thuận xu hướng, vào theo style.",
    "scalp": {
     "dir": "LONG",
     "entry": [
      576.42,
      577.4
     ],
     "sl": 574.78,
     "tp": [
      578.37,
      581.54,
      586.66
     ],
     "rr": 2.18,
     "method": "fib",
     "fib": {
      "f0": 573.25,
      "f382": 578.37,
      "f500": 577.4,
      "f618": 576.42,
      "f786": 575.02,
      "f100": 581.54,
      "ext1618": 586.66
     },
     "meetsMinRR": true,
     "reasons": [
      "VWAP↑",
      "RSI88"
     ]
    },
    "day": {
     "dir": "LONG",
     "entry": [
      579,
      581
     ],
     "sl": 577,
     "tp": [
      584,
      588
     ],
     "rr": 2.6,
     "method": "atr",
     "reasons": [
      "VWAP↑",
      "RSI65"
     ]
    },
    "swing": {
     "dir": "LONG",
     "entry": [
      562,
      581
     ],
     "sl": 557,
     "tp": [
      618,
      630,
      655
     ],
     "rr": 3.9,
     "method": "atr-fallback",
     "fib": null
    }
   },
   "indicators": [
    {
     "tf": "1D",
     "rsi": 50.58,
     "macd": "bull",
     "stoch": 78.9,
     "st": "down",
     "extra": "ADX 15 · EMA death"
    },
    {
     "tf": "4H",
     "rsi": 58.73,
     "macd": "bull",
     "stoch": 95.85,
     "st": "up",
     "extra": "Ichi above"
    },
    {
     "tf": "1H",
     "rsi": 65,
     "macd": "bull",
     "stoch": 96,
     "st": 1,
     "extra": "VWAP above"
    },
    {
     "tf": "15m",
     "rsi": 88,
     "macd": "bull",
     "stoch": 96,
     "st": 1,
     "extra": ""
    }
   ],
   "cycle": {
    "regime": "DEEP BEAR / vùng đáy chu kỳ",
    "ma200w": null,
    "mayer": 0.86,
    "weeklyMacdBear": true,
    "supports": [],
    "piGapPct": null
   },
   "derivatives": {
    "fundingRate": -0.000001,
    "coinbasePremium": {
     "gap": -0.14,
     "signal": "⚪ trung tính"
    }
   },
   "levels": [
    {
     "price": 581,
     "label": "Entry LONG",
     "color": "#22c55e"
    },
    {
     "price": 557,
     "label": "SL",
     "color": "#f59e0b"
    },
    {
     "price": 618,
     "label": "TP1",
     "color": "#3b82f6"
    },
    {
     "price": 560.93,
     "label": "Hỗ trợ",
     "color": "#64748b"
    }
   ]
  },
  "XAU": {
   "symbol": "XAU",
   "tvSymbol": "OKX:XAUUSDT.P",
   "liveBase": "PAXG",
   "price": {
    "last": 4099.13,
    "change24h": -0.35,
    "high24h": 4115.25,
    "low24h": 4098.23
   },
   "council": {
    "direction": "SHORT",
    "confidence": "low",
    "consensus": -0.191,
    "agreement": 57,
    "counterTrend": false,
    "tiers": {
     "regime": {
      "dir": "SHORT",
      "score": -0.5
     },
     "setup": {
      "dir": "LONG",
      "gated": true
     },
     "trigger": {
      "dir": "NEUTRAL",
      "gated": false
     }
    },
    "members": [
     {
      "name": "Trend",
      "vote": -1,
      "weight": 2.47,
      "tier": "regime",
      "dot": "red"
     },
     {
      "name": "Patterns",
      "vote": 1,
      "weight": 1.85,
      "tier": "setup",
      "dot": "green"
     },
     {
      "name": "Cycle",
      "vote": -0.5,
      "weight": 1.2,
      "tier": "regime",
      "dot": "red"
     },
     {
      "name": "SMC",
      "vote": -0.27,
      "weight": 1.53,
      "tier": "setup",
      "dot": "red"
     },
     {
      "name": "Volume",
      "vote": -0.3,
      "weight": 0.91,
      "tier": "trigger",
      "dot": "red"
     },
     {
      "name": "Sentiment",
      "vote": 0.3,
      "weight": 1,
      "tier": "regime",
      "dot": "green"
     },
     {
      "name": "Macro",
      "vote": -0.53,
      "weight": 0.5,
      "tier": "regime",
      "dot": "red"
     },
     {
      "name": "Momentum",
      "vote": -0.16,
      "weight": 1.39,
      "tier": "trigger",
      "dot": "red"
     },
     {
      "name": "Ichimoku",
      "vote": 0.1,
      "weight": 1.94,
      "tier": "regime",
      "dot": "green"
     },
     {
      "name": "Derivatives",
      "vote": 0.15,
      "weight": 0.7,
      "tier": "trigger",
      "dot": "green"
     },
     {
      "name": "MeanReversion",
      "vote": 0,
      "weight": 0.63,
      "tier": "setup",
      "dot": "gray"
     },
     {
      "name": "ETFFlow",
      "vote": 0,
      "weight": 1.2,
      "tier": "regime",
      "dot": "gray"
     }
    ]
   },
   "expert": {
    "verdict": "3 khung đồng pha SHORT — thuận xu hướng, vào theo style.",
    "scalp": {
     "dir": "SHORT",
     "entry": [
      4101,
      4101
     ],
     "sl": 4102,
     "tp": [
      4100,
      4098,
      4095
     ],
     "rr": 2.18,
     "method": "fib",
     "fib": {
      "f0": 4103,
      "f382": 4100,
      "f500": 4101,
      "f618": 4101,
      "f786": 4102,
      "f100": 4098,
      "ext1618": 4095
     },
     "meetsMinRR": true,
     "reasons": [
      "VWAP↓",
      "RSI41"
     ]
    },
    "day": {
     "dir": "SHORT",
     "entry": [
      4107,
      4109
     ],
     "sl": 4113,
     "tp": [
      4105,
      4098,
      4087
     ],
     "rr": 2.18,
     "method": "fib",
     "fib": {
      "f0": 4116,
      "f382": 4105,
      "f500": 4107,
      "f618": 4109,
      "f786": 4112,
      "f100": 4098,
      "ext1618": 4087
     },
     "meetsMinRR": true,
     "reasons": [
      "VWAP↓",
      "RSI39"
     ]
    },
    "swing": {
     "dir": "SHORT",
     "entry": [
      4082,
      4097
     ],
     "sl": 4121,
     "tp": [
      4068,
      4021,
      3946
     ],
     "rr": 2.2,
     "method": "fibonacci",
     "fib": {
      "f0": 4143,
      "f382": 4068,
      "f500": 4082,
      "f618": 4097,
      "f786": 4117,
      "f100": 4021,
      "ext1618": 3946
     },
     "meetsMinRR": true
    }
   },
   "indicators": [
    {
     "tf": "1D",
     "rsi": 44.32,
     "macd": "bull",
     "stoch": 61.7,
     "st": "down",
     "extra": "ADX 38 · EMA death"
    },
    {
     "tf": "4H",
     "rsi": 45.82,
     "macd": "bear",
     "stoch": 61.39,
     "st": "down",
     "extra": "Ichi inside"
    },
    {
     "tf": "1H",
     "rsi": 39,
     "macd": "bear",
     "stoch": 17,
     "st": -1,
     "extra": "VWAP below"
    },
    {
     "tf": "15m",
     "rsi": 41,
     "macd": "bull",
     "stoch": 5,
     "st": -1,
     "extra": ""
    }
   ],
   "cycle": {
    "regime": "Pullback/bear-rally (giữa MA200W và MA50W)",
    "ma200w": 2817.15,
    "mayer": 0.88,
    "weeklyMacdBear": true,
    "supports": [
     {
      "ma": "MA200W",
      "level": 2817,
      "distPct": -31.3
     }
    ],
    "piGapPct": 46.6
   },
   "derivatives": {
    "fundingRate": -0.000054,
    "coinbasePremium": {
     "gap": -2.54,
     "signal": "⚪ trung tính"
    }
   },
   "levels": [
    {
     "price": 4097,
     "label": "Entry SHORT",
     "color": "#ef4444"
    },
    {
     "price": 4121,
     "label": "SL",
     "color": "#f59e0b"
    },
    {
     "price": 4068,
     "label": "TP1",
     "color": "#3b82f6"
    },
    {
     "price": 2817.15,
     "label": "MA200W",
     "color": "#a855f7"
    },
    {
     "price": 4021,
     "label": "Hỗ trợ",
     "color": "#64748b"
    }
   ]
  }
 },
 "btcExtra": {
  "etf": {
   "latestNetInflowUsd": 90439970,
   "net7DaysUsd": 124499948.68
  },
  "etfMetrics": {
   "totalNetAssetsUsd": 77421550348.27,
   "pctOfMcap": 0.06047062,
   "dailyNetInflowUsd": 90439970,
   "cumNetInflowUsd": 51295025532.013,
   "dailyValueTradedUsd": 1448656623,
   "totalBtcHeld": 1212752.43422508,
   "topIssuer": {
    "ticker": "IBIT",
    "institute": "BlackRock",
    "netAssetsUsd": 46904053440,
    "pctOfMcap": 0.03663472
   },
   "asOf": "2026-07-10"
  },
  "sentiment": {
   "fearGreed": {
    "value": 26,
    "classification": "Fear",
    "history": [
     {
      "value": 26,
      "classification": "Fear"
     },
     {
      "value": 26,
      "classification": "Fear"
     },
     {
      "value": 23,
      "classification": "Extreme Fear"
     },
     {
      "value": 22,
      "classification": "Extreme Fear"
     },
     {
      "value": 20,
      "classification": "Extreme Fear"
     },
     {
      "value": 27,
      "classification": "Fear"
     },
     {
      "value": 24,
      "classification": "Extreme Fear"
     }
    ]
   },
   "news": {
    "source": "6551",
    "articles": 30,
    "scored": 24,
    "avgScore": 44,
    "longCount": 5,
    "shortCount": 9,
    "neutralCount": 10,
    "net": "short",
    "headlines": [
     "Omani Foreign Ministry: We call on Iran to adhere to the provisions of state sovereignty a",
     "CNN on tracking data: Navigation traffic through the Strait of Hormuz has noticeably decli",
     "Trump on the sudden passing of Senator Lindsey Graham https://t.co/LGPOouE3Sh"
    ]
   },
   "community": {
    "source": "coingecko",
    "upPct": 75.3,
    "downPct": 24.8,
    "net": "long"
   },
   "divergence": "rumor_bull_news_bear"
  },
  "breadth": {
   "count": 12,
   "green": 2,
   "pctGreen": 17,
   "avgChange": -1.72,
   "btcChange": -0.51,
   "avgAltChange": -1.83,
   "altsOutperform": false
  },
  "macro": {
   "btcDominance": 56.24,
   "ethDominance": 9.54,
   "usdtDominance": 8.07,
   "usdcDominance": 3.22,
   "stablecoinDominance": 11.29,
   "totalMarketCapUsd": 2280831324083,
   "mcapChange24h": -0.21,
   "interpretation": "Stablecoin dominance cao → tiền đứng ngoài, tâm lý risk-off (thận trọng với alt)"
  },
  "macroEvents": [
   {
    "date": "2026-07-13",
    "events": [
     "CPI (MoM)",
     "Core CPI (MoM)",
     "CPI (YoY)"
    ],
    "high": true
   },
   {
    "date": "2026-07-14",
    "events": [
     "PPI (MoM)"
    ],
    "high": true
   },
   {
    "date": "2026-07-15",
    "events": [
     "Retail Sales (MoM)"
    ],
    "high": true
   },
   {
    "date": "2026-07-23",
    "events": [
     "S&P Global US Manufacturing PMI",
     "S&P Global Services PMI",
     "New Home Sales"
    ],
    "high": false
   }
  ],
  "fundingHistory": [
   {
    "time": 1782489600,
    "rate": 0.000011
   },
   {
    "time": 1782518400,
    "rate": 0.000057
   },
   {
    "time": 1782547200,
    "rate": 0.000037
   },
   {
    "time": 1782576000,
    "rate": -0.000036
   },
   {
    "time": 1782604800,
    "rate": 0.000025
   },
   {
    "time": 1782633600,
    "rate": 0.000061
   },
   {
    "time": 1782662400,
    "rate": 0.000026
   },
   {
    "time": 1782691200,
    "rate": 0.000047
   },
   {
    "time": 1782720000,
    "rate": -0.000014
   },
   {
    "time": 1782748800,
    "rate": 0.000049
   },
   {
    "time": 1782777600,
    "rate": 0.000028
   },
   {
    "time": 1782806400,
    "rate": 0.000025
   },
   {
    "time": 1782835200,
    "rate": 0.000075
   },
   {
    "time": 1782864000,
    "rate": 0.000089
   },
   {
    "time": 1782892800,
    "rate": 0.000089
   },
   {
    "time": 1782921600,
    "rate": 0.000091
   },
   {
    "time": 1782950400,
    "rate": 0.000088
   },
   {
    "time": 1782979200,
    "rate": 0.000063
   },
   {
    "time": 1783008000,
    "rate": 0.000042
   },
   {
    "time": 1783036800,
    "rate": 0.000121
   },
   {
    "time": 1783065600,
    "rate": 0.000162
   },
   {
    "time": 1783094400,
    "rate": 0.000017
   },
   {
    "time": 1783123200,
    "rate": -0.000002
   },
   {
    "time": 1783152000,
    "rate": 0.000067
   },
   {
    "time": 1783180800,
    "rate": 0.000051
   },
   {
    "time": 1783209600,
    "rate": -0.000006
   },
   {
    "time": 1783238400,
    "rate": 0.000009
   },
   {
    "time": 1783267200,
    "rate": 0.000018
   },
   {
    "time": 1783296000,
    "rate": 0.000025
   },
   {
    "time": 1783324800,
    "rate": -0.000011
   },
   {
    "time": 1783353600,
    "rate": 0.00011
   },
   {
    "time": 1783382400,
    "rate": 0.000055
   },
   {
    "time": 1783411200,
    "rate": 0.000116
   },
   {
    "time": 1783440000,
    "rate": 0.000045
   },
   {
    "time": 1783468800,
    "rate": 0.000037
   },
   {
    "time": 1783497600,
    "rate": 0.000022
   },
   {
    "time": 1783526400,
    "rate": 0.000049
   },
   {
    "time": 1783555200,
    "rate": 0.000061
   },
   {
    "time": 1783584000,
    "rate": 0.000027
   },
   {
    "time": 1783612800,
    "rate": 0.000022
   },
   {
    "time": 1783641600,
    "rate": 0.000024
   },
   {
    "time": 1783670400,
    "rate": 0.000053
   },
   {
    "time": 1783699200,
    "rate": 0.000053
   },
   {
    "time": 1783728000,
    "rate": 0.000052
   },
   {
    "time": 1783756800,
    "rate": -0.000046
   },
   {
    "time": 1783785600,
    "rate": -0.000011
   },
   {
    "time": 1783814400,
    "rate": 0.000027
   },
   {
    "time": 1783843200,
    "rate": 0.000021
   }
  ],
  "paper": {
   "startCapital": 10000,
   "marginPerTrade": 1000,
   "feeRate": 0.0005,
   "primary": "lev30",
   "arms": [
    {
     "id": "lev30",
     "label": "30x (guard SL)",
     "desc": "≤30x guard",
     "capital": 9834.47,
     "net": -165.53,
     "netPct": -1.66,
     "open": 2,
     "positions": [
      {
       "style": "day",
       "dir": "LONG",
       "entry": 64176.4,
       "sl": 63588,
       "slOrig": 63588,
       "tp": [
        64672,
        65165
       ],
       "tp1Hit": false,
       "liq": 62037.19,
       "margin": 1000,
       "leverage": 30,
       "notional": 30000,
       "lastPrice": 63991.8,
       "remaining": 1,
       "realizedUsd": 0,
       "tpHits": 0
      },
      {
       "style": "swing",
       "dir": "SHORT",
       "entry": 64328.5,
       "sl": 65384,
       "slOrig": 65384,
       "tp": [
        62717,
        62183,
        61116
       ],
       "tp1Hit": false,
       "liq": 66472.78,
       "margin": 1000,
       "leverage": 30,
       "notional": 30000,
       "lastPrice": 63991.8,
       "remaining": 1,
       "realizedUsd": 0,
       "tpHits": 0
      }
     ],
     "stats": {
      "trades": 3,
      "wins": 0,
      "winRate": 0,
      "liquidations": 0,
      "net": -165.53,
      "maxDD": 1.7
     }
    },
    {
     "id": "lev10",
     "label": "10x (guard SL)",
     "desc": "≤10x guard",
     "capital": 9944.82,
     "net": -55.18,
     "netPct": -0.55,
     "open": 2,
     "positions": [
      {
       "style": "day",
       "dir": "LONG",
       "entry": 64176.4,
       "sl": 63588,
       "slOrig": 63588,
       "tp": [
        64672,
        65165
       ],
       "tp1Hit": false,
       "liq": 57758.76,
       "margin": 1000,
       "leverage": 10,
       "notional": 10000,
       "lastPrice": 63991.8,
       "remaining": 1,
       "realizedUsd": 0,
       "tpHits": 0
      },
      {
       "style": "swing",
       "dir": "SHORT",
       "entry": 64328.5,
       "sl": 65384,
       "slOrig": 65384,
       "tp": [
        62717,
        62183,
        61116
       ],
       "tp1Hit": false,
       "liq": 70761.35,
       "margin": 1000,
       "leverage": 10,
       "notional": 10000,
       "lastPrice": 63991.8,
       "remaining": 1,
       "realizedUsd": 0,
       "tpHits": 0
      }
     ],
     "stats": {
      "trades": 3,
      "wins": 0,
      "winRate": 0,
      "liquidations": 0,
      "net": -55.18,
      "maxDD": 0.6
     }
    },
    {
     "id": "risk",
     "label": "Risk 1.5%/lệnh",
     "desc": "risk 1.5% (lev theo SL)",
     "capital": 9862.05,
     "net": -137.95,
     "netPct": -1.38,
     "open": 2,
     "positions": [
      {
       "style": "day",
       "dir": "LONG",
       "entry": 64176.4,
       "sl": 63588,
       "slOrig": 63588,
       "tp": [
        64672,
        65165
       ],
       "tp1Hit": false,
       "liq": 60263.2,
       "margin": 1000,
       "leverage": 16.4,
       "notional": 16360,
       "lastPrice": 63991.8,
       "remaining": 1,
       "realizedUsd": 0,
       "tpHits": 0
      },
      {
       "style": "swing",
       "dir": "SHORT",
       "entry": 64328.5,
       "sl": 65384,
       "slOrig": 65384,
       "tp": [
        62717,
        62183,
        61116
       ],
       "tp1Hit": false,
       "liq": 71397.57,
       "margin": 1000,
       "leverage": 9.1,
       "notional": 9100,
       "lastPrice": 63991.8,
       "remaining": 1,
       "realizedUsd": 0,
       "tpHits": 0
      }
     ],
     "stats": {
      "trades": 3,
      "wins": 0,
      "winRate": 0,
      "liquidations": 0,
      "net": -137.95,
      "maxDD": 1.4
     }
    }
   ],
   "analysis": {
    "overall": {
     "trades": 3,
     "wins": 0,
     "winRate": 0,
     "net": -165.53,
     "avgPct": -5.52,
     "profitFactor": 0,
     "liquidations": 0
    },
    "byStyle": {
     "scalp": {
      "trades": 3,
      "wins": 0,
      "winRate": 0,
      "net": -165.53,
      "avgPct": -5.52,
      "profitFactor": 0,
      "liquidations": 0
     },
     "day": {
      "trades": 0,
      "wins": 0,
      "winRate": 0,
      "net": 0,
      "avgPct": 0,
      "profitFactor": 0,
      "liquidations": 0
     },
     "swing": {
      "trades": 0,
      "wins": 0,
      "winRate": 0,
      "net": 0,
      "avgPct": 0,
      "profitFactor": 0,
      "liquidations": 0
     }
    },
    "byDir": {
     "LONG": {
      "trades": 1,
      "wins": 0,
      "winRate": 0,
      "net": -93.19,
      "avgPct": -9.32,
      "profitFactor": 0,
      "liquidations": 0
     },
     "SHORT": {
      "trades": 2,
      "wins": 0,
      "winRate": 0,
      "net": -72.34,
      "avgPct": -3.61,
      "profitFactor": 0,
      "liquidations": 0
     }
    },
    "maxConsecLoss": 3
   },
   "history": [
    {
     "style": "scalp",
     "dir": "SHORT",
     "entry": 63941,
     "exit": 63941,
     "sl": 64124,
     "tp": [
      63873,
      63653,
      63296
     ],
     "outcome": "PARTIAL",
     "tpHits": 1,
     "leverage": 30,
     "pnlUsd": -17.24,
     "pnlPct": -1.72,
     "openedAt": "16:22 12-07 GMT+7",
     "closedAt": "18:49 12-07 GMT+7"
    },
    {
     "style": "scalp",
     "dir": "LONG",
     "entry": 64232.3,
     "exit": 64097,
     "sl": 64097,
     "tp": [
      64427,
      64568
     ],
     "outcome": "SL",
     "tpHits": 0,
     "leverage": 30,
     "pnlUsd": -93.19,
     "pnlPct": -9.32,
     "openedAt": "00:27 12-07 GMT+7",
     "closedAt": "06:39 12-07 GMT+7"
    },
    {
     "style": "scalp",
     "dir": "SHORT",
     "entry": 64188.3,
     "exit": 64242,
     "sl": 64242,
     "tp": [
      64090,
      64025
     ],
     "outcome": "SL",
     "tpHits": 0,
     "leverage": 30,
     "pnlUsd": -55.1,
     "pnlPct": -5.51,
     "openedAt": "19:43 11-07 GMT+7",
     "closedAt": "21:15 11-07 GMT+7"
    }
   ],
   "historyTotal": {
    "trades": 3,
    "pnlUsd": -165.53
   },
   "recent": [
    {
     "style": "scalp",
     "dir": "SHORT",
     "entry": 63941,
     "exit": 63941,
     "sl": 64124,
     "tp": [
      63873,
      63653,
      63296
     ],
     "outcome": "PARTIAL",
     "tpHits": 1,
     "leverage": 30,
     "pnlUsd": -17.24,
     "pnlPct": -1.72,
     "openedAt": "16:22 12-07 GMT+7",
     "closedAt": "18:49 12-07 GMT+7"
    },
    {
     "style": "scalp",
     "dir": "LONG",
     "entry": 64232.3,
     "exit": 64097,
     "sl": 64097,
     "tp": [
      64427,
      64568
     ],
     "outcome": "SL",
     "tpHits": 0,
     "leverage": 30,
     "pnlUsd": -93.19,
     "pnlPct": -9.32,
     "openedAt": "00:27 12-07 GMT+7",
     "closedAt": "06:39 12-07 GMT+7"
    },
    {
     "style": "scalp",
     "dir": "SHORT",
     "entry": 64188.3,
     "exit": 64242,
     "sl": 64242,
     "tp": [
      64090,
      64025
     ],
     "outcome": "SL",
     "tpHits": 0,
     "leverage": 30,
     "pnlUsd": -55.1,
     "pnlPct": -5.51,
     "openedAt": "19:43 11-07 GMT+7",
     "closedAt": "21:15 11-07 GMT+7"
    }
   ],
   "updatedAt": "18:49 12-07 GMT+7"
  },
  "bottom": {
   "count": 1,
   "total": 7,
   "verdict": "chưa rõ",
   "active": [
    "Cửa sổ đáy 111–132w (tuần 116)"
   ],
   "halving": {
    "lastHalving": "2024-04-19",
    "weeksSince": 116.4,
    "phase": "bottomWindow",
    "label": "🎯 CỬA SỔ ĐÁY chu kỳ (lịch sử: đáy tuần 111/127/132)",
    "inBottomWindow": true,
    "inProfitWindow": false,
    "bottomWindow": {
     "from": "2026-06-05",
     "to": "2026-10-30"
    },
    "profitWindow": {
     "from": "2025-01-24",
     "to": "2025-10-31"
    },
    "dcaStart": "2026-11-20",
    "nextHalvingPredicted": "2028-02-04",
    "nextProfitWindow": {
     "from": "2028-11-10",
     "to": "2029-08-17"
    }
   }
  }
 }
}